odoo/addons/energy_communities_crm_lead_mail_fix/README.md
odoo/addons/energy_communities_crm_lead_mail_fix/__init__.py
odoo/addons/energy_communities_crm_lead_mail_fix/__manifest__.py
odoo/addons/energy_communities_crm_lead_mail_fix/pyproject.toml
odoo/addons/energy_communities_crm_lead_mail_fix/data/partner_tags.xml
odoo/addons/energy_communities_crm_lead_mail_fix/models/__init__.py
odoo/addons/energy_communities_crm_lead_mail_fix/models/crm_lead.py
odoo_addon_energy_communities_crm_lead_mail_fix-16.0.0.1.0.3.dist-info/METADATA
odoo_addon_energy_communities_crm_lead_mail_fix-16.0.0.1.0.3.dist-info/WHEEL
odoo_addon_energy_communities_crm_lead_mail_fix-16.0.0.1.0.3.dist-info/top_level.txt
odoo_addon_energy_communities_crm_lead_mail_fix-16.0.0.1.0.3.dist-info/RECORD
